LICENSE
MANIFEST.in
README.md
setup.py
djangoshortcuts/__init__.py
djangoshortcuts/__main__.py
djangoshortcuts/command.py
djangoshortcuts.egg-info/PKG-INFO
djangoshortcuts.egg-info/SOURCES.txt
djangoshortcuts.egg-info/dependency_links.txt
djangoshortcuts.egg-info/entry_points.txt
djangoshortcuts.egg-info/top_level.txt