Metadata-Version: 2.1
Name: djangoshortcuts
Version: 0.0.2
Summary: Shortcuts to create files easily when using django
Home-page: https://github.com/suifengpiaoyang/djangoshortcuts
Author: Zhang
Author-email: 
License: MIT
Platform: UNKNOWN
Classifier: Programming Language :: Python :: 3
Classifier: License :: OSI Approved :: MIT License
Classifier: Operating System :: OS Independent
Requires-Python: >=3.5.2
